iterxml.py
setup.py
iterxml.egg-info/PKG-INFO
iterxml.egg-info/SOURCES.txt
iterxml.egg-info/dependency_links.txt
iterxml.egg-info/top_level.txt