Metadata-Version: 1.0
Name: iterxml
Version: 0.1.1
Summary: Stream data from large XML documents with minimal memory.
Home-page: http://bitbucket.org/lars512/iterxml/
Author: Lars Yencken
Author-email: lljy@csse.unimelb.edu.au
License: BSD
Platform: UNKNOWN
